evan/__init__.py
evan/config.py
evan/dataset.py
evan/inception.py
evan/score.py
evan/metrics/__init__.py
evan/metrics/frechet_distance.py
evan/metrics/inception_score.py
evan/metrics/precision_recall_distributions.py
evan/models/__init__.py
evan/models/resnet.py
evan-0.0.2.dist-info/METADATA
evan-0.0.2.dist-info/WHEEL
evan-0.0.2.dist-info/entry_points.txt
evan-0.0.2.dist-info/top_level.txt
evan-0.0.2.dist-info/RECORD
