Metadata-Version: 2.1
Name: evan
Version: 0.0.2
Summary: Evaluation framework for GANs for video generation
Home-page: https://github.com/raahii/video-gans-evaluation
Author: raahii
License: UNKNOWN
Platform: UNKNOWN
Requires-Python: >=3.4
Requires-Dist: requests
Requires-Dist: googledrivedownloader
Requires-Dist: tqdm
Requires-Dist: torch (==1.2.0)
Requires-Dist: scikit-video
Requires-Dist: opencv-python
Requires-Dist: scikit-learn
Requires-Dist: matplotlib
Requires-Dist: numpy
